[
    {        
        "fullname": "Имя Фамилия",
        "position": "Должность"
    },
    {        
        "fullname": "Имя Фамилия",
        "position": "Должность"
    },
    {        
        "fullname": "Имя Фамилия",
        "position": "Должность"
    },
    {        
        "fullname": "Имя Фамилия",
        "position": "Должность"
    },
    {        
        "fullname": "Имя Фамилия",
        "position": "Должность"
    },
    {        
        "fullname": "Имя Фамилия",
        "position": "Должность"
    },
    {        
        "fullname": "Имя Фамилия",
        "position": "Должность"
    },
    {        
        "fullname": "Имя Фамилия",
        "position": "Должность"
    }
]